ringcentral_async_client/__init__.py
ringcentral_async_client/client.py
ringcentral_async_client/model.py
ringcentral_async_client/utils.py
ringcentral_async_client/_code_gen/__init__.py
ringcentral_async_client/_code_gen/client.py
ringcentral_async_client/_code_gen/utils.py
ringcentral_async_client/_code_gen/model/_1.py
ringcentral_async_client/_code_gen/model/_10.py
ringcentral_async_client/_code_gen/model/_11.py
ringcentral_async_client/_code_gen/model/_12.py
ringcentral_async_client/_code_gen/model/_13.py
ringcentral_async_client/_code_gen/model/_14.py
ringcentral_async_client/_code_gen/model/_15.py
ringcentral_async_client/_code_gen/model/_16.py
ringcentral_async_client/_code_gen/model/_2.py
ringcentral_async_client/_code_gen/model/_3.py
ringcentral_async_client/_code_gen/model/_4.py
ringcentral_async_client/_code_gen/model/_5.py
ringcentral_async_client/_code_gen/model/_6.py
ringcentral_async_client/_code_gen/model/_7.py
ringcentral_async_client/_code_gen/model/_8.py
ringcentral_async_client/_code_gen/model/_9.py
ringcentral_async_client/_code_gen/model/__init__.py
ringcentral_async_client-1.0.3.dist-info/LICENSE.txt
ringcentral_async_client-1.0.3.dist-info/METADATA
ringcentral_async_client-1.0.3.dist-info/WHEEL
ringcentral_async_client-1.0.3.dist-info/namespace_packages.txt
ringcentral_async_client-1.0.3.dist-info/top_level.txt
ringcentral_async_client-1.0.3.dist-info/RECORD
