Metadata-Version: 2.1
Name: ringcentral-async-client
Version: 1.0.3
Summary: Asynchronous client for the RingCentral Platform, based on Tornado and generated via Python OpenAPI Parser
Home-page: https://gitlab.com/Hares-Lab/ringcentral-async-client
License: MIT License
Platform: UNKNOWN
Classifier: Development Status :: 2 - Pre-Alpha
Classifier: Intended Audience :: Developers
Classifier: License :: OSI Approved :: MIT License
Classifier: Natural Language :: English
Classifier: Operating System :: OS Independent
Classifier: Programming Language :: Python :: 3.6
Classifier: Programming Language :: Python :: 3.7
Classifier: Programming Language :: Python :: 3.8
Classifier: Programming Language :: Python :: 3.9
Classifier: Topic :: Communications :: Chat
Classifier: Topic :: Communications :: Conferencing
Classifier: Topic :: Communications :: Telephony
Classifier: Topic :: Communications
Classifier: Topic :: Internet
Classifier: Topic :: Software Development :: Libraries :: Python Modules
Classifier: Topic :: Software Development :: Libraries
Classifier: Topic :: Utilities
Requires-Python: >=3.6.0
Requires-Dist: dataclasses-json (>=0.5.2)
Requires-Dist: functional-python (~=0.0.9)
Requires-Dist: http-server-base (>=2.0.1)
Requires-Dist: tornado (>=6.0.4)
Requires-Dist: dataclasses (>=0.6) ; python_version < "3.7"
Provides-Extra: all
